hera/__init__.py
hera/__main__.py
hera/_cli/__init__.py
hera/_cli/base.py
hera/_cli/generate/__init__.py
hera/_cli/generate/python.py
hera/_cli/generate/util.py
hera/_cli/generate/yaml.py
hera/_version.py
hera/_yaml.py
hera/auth/__init__.py
hera/events/__init__.py
hera/events/async_service.py
hera/events/models/__init__.py
hera/events/models/eventsource.py
hera/events/models/github/__init__.py
hera/events/models/github/com/__init__.py
hera/events/models/github/com/argoproj/__init__.py
hera/events/models/github/com/argoproj/argo_events/__init__.py
hera/events/models/github/com/argoproj/argo_events/pkg/__init__.py
hera/events/models/github/com/argoproj/argo_events/pkg/apis/__init__.py
hera/events/models/github/com/argoproj/argo_events/pkg/apis/events/__init__.py
hera/events/models/github/com/argoproj/argo_events/pkg/apis/events/v1alpha1.py
hera/events/models/google/__init__.py
hera/events/models/google/protobuf.py
hera/events/models/grpc/__init__.py
hera/events/models/grpc/gateway/__init__.py
hera/events/models/grpc/gateway/runtime.py
hera/events/models/io/__init__.py
hera/events/models/io/argoproj/__init__.py
hera/events/models/io/argoproj/workflow/__init__.py
hera/events/models/io/argoproj/workflow/v1alpha1.py
hera/events/models/io/k8s/__init__.py
hera/events/models/io/k8s/api/__init__.py
hera/events/models/io/k8s/api/core/__init__.py
hera/events/models/io/k8s/api/core/v1.py
hera/events/models/io/k8s/api/policy/__init__.py
hera/events/models/io/k8s/api/policy/v1.py
hera/events/models/io/k8s/apimachinery/__init__.py
hera/events/models/io/k8s/apimachinery/pkg/__init__.py
hera/events/models/io/k8s/apimachinery/pkg/api/__init__.py
hera/events/models/io/k8s/apimachinery/pkg/api/resource.py
hera/events/models/io/k8s/apimachinery/pkg/apis/__init__.py
hera/events/models/io/k8s/apimachinery/pkg/apis/meta/__init__.py
hera/events/models/io/k8s/apimachinery/pkg/apis/meta/v1.py
hera/events/models/io/k8s/apimachinery/pkg/util/__init__.py
hera_workflows-5.27.0.dist-info/METADATA
hera_workflows-5.27.0.dist-info/WHEEL
hera_workflows-5.27.0.dist-info/entry_points.txt
hera_workflows-5.27.0.dist-info/licenses/LICENSE
hera_workflows-5.27.0.dist-info/RECORD
